[
  {
    "title": "task1",
    "status": "created"
  },
  {
    "id": "1775017770265",
    "title": "Test",
    "content": "Hello"
  },
  {
    "id": "1775024121404",
    "title": "NODE JS",
    "content": "LETS LEARN NODE JS",
    "status": "created"
  },
  {
    "id": "1775024883636",
    "title": "Test",
    "content": "Hello",
    "status": "created"
  },
  {
    "id": "1775024883693",
    "title": "NODE JS",
    "content": "LETS LEARN NODE JS",
    "status": "created"
  },

  {
    "id": "1775032925835",
    "title": "Test",
    "content": "Hello",
    "status": "created",
    "createdAt": "2026-04-01T08:42:05.835Z"
  },
  {
    "id": "1775032925887",
    "title": "new",
    "content": "new",
    "status": "created",
    "createdAt": "2026-04-01T08:42:05.887Z",
    "updatedAt": "2026-04-01T08:42:05.892Z"
  },
  {
    "id": "1775032925910",
    "title": "x",
    "content": "y",
    "status": "created",
    "createdAt": "2026-04-01T08:42:05.910Z",
    "updatedAt": "2026-04-01T08:42:05.914Z"
  },
  {
    "id": "1775034632412",
    "title": "NODE JS",
    "content": "LETS LEARN NODE JS",
    "status": "created",
    "createdAt": "2026-04-01T09:10:32.412Z"
  },
  {
    "id": "1775035157720",
    "title": "Test",
    "content": "Hello",
    "status": "created",
    "createdAt": "2026-04-01T09:19:17.720Z"
  },
  {
    "id": "1775035157889",
    "title": "x",
    "content": "y",
    "status": "created",
    "createdAt": "2026-04-01T09:19:17.889Z",
    "updatedAt": "2026-04-01T09:19:17.894Z"
  },
  {
    "id": "1775036112513",
    "title": "new",
    "content": "new",
    "status": "created",
    "createdAt": "2026-04-01T09:35:12.513Z",
    "updatedAt": "2026-04-01T09:35:12.517Z"
  },
  {
    "id": "1775036112534",
    "title": "x",
    "content": "y",
    "status": "created",
    "createdAt": "2026-04-01T09:35:12.534Z",
    "updatedAt": "2026-04-01T09:35:12.538Z"
  },
  {
    "id": 1775206245225,
    "text": "Memory 1 ZetaByte",
    "status": "closed"
  },
  {
    "id": 1775208131604,
    "text": "Speed 1 TeraHertz",
    "status": "open"
  },
  {
    "id": 1775208145515,
    "text": "JAVA ",
    "status": "open"
  },
  {
    "id": 1775208171904,
    "text": "Memory 1 ZetaByte",
    "status": "open"
  }
 
]